<?xml version="1.0" encoding="utf-8"?>
    <annotation>
		<size>     
		    <width>1920</width>
		    <height>1080</height>
		    <depth>3</depth>
	    </size>

	<filename>000819.jpg</filename>
	
    <object>
		<pose>Unspecified</pose>
		<truncated>0</truncated>
		<difficult>0</difficult>

		<name>scallop</name>
		<bndbox>
			<xmin>2785</xmin>
			<ymin>729</ymin>
			<xmax>3026</xmax>
			<ymax>862</ymax>
		</bndbox>
	</object>
	
    <object>
		<pose>Unspecified</pose>
		<truncated>0</truncated>
		<difficult>0</difficult>

		<name>scallop</name>
		<bndbox>
			<xmin>293</xmin>
			<ymin>1182</ymin>
			<xmax>508</xmax>
			<ymax>1313</ymax>
		</bndbox>
	</object>
	
    <object>
		<pose>Unspecified</pose>
		<truncated>0</truncated>
		<difficult>0</difficult>

		<name>scallop</name>
		<bndbox>
			<xmin>1706</xmin>
			<ymin>1521</ymin>
			<xmax>1961</xmax>
			<ymax>1726</ymax>
		</bndbox>
	</object>
	
    <object>
		<pose>Unspecified</pose>
		<truncated>0</truncated>
		<difficult>0</difficult>

		<name>scallop</name>
		<bndbox>
			<xmin>1903</xmin>
			<ymin>556</ymin>
			<xmax>2059</xmax>
			<ymax>702</ymax>
		</bndbox>
	</object>
</annotation>