<?xml version="1.0" encoding="utf-8"?>
    <annotation>
		<size>     
		    <width>1920</width>
		    <height>1080</height>
		    <depth>3</depth>
	    </size>

   <filename>002419.jpg</filename>
   
    <object>
		<pose>Unspecified</pose>
		<truncated>0</truncated>
		<difficult>0</difficult>

      <name>holothurian</name>
      <bndbox>
         <xmin>197</xmin>
         <ymin>177</ymin>
         <xmax>240</xmax>
         <ymax>246</ymax>
      </bndbox>
   </object>
   
    <object>
		<pose>Unspecified</pose>
		<truncated>0</truncated>
		<difficult>0</difficult>

      <name>holothurian</name>
      <bndbox>
         <xmin>97</xmin>
         <ymin>253</ymin>
         <xmax>149</xmax>
         <ymax>323</ymax>
      </bndbox>
   </object>
</annotation>