<?xml version="1.0" encoding="utf-8"?>
    <annotation>
		<size>     
		    <width>1920</width>
		    <height>1080</height>
		    <depth>3</depth>
	    </size>

   <filename>002689.jpg</filename>
   
    <object>
		<pose>Unspecified</pose>
		<truncated>0</truncated>
		<difficult>0</difficult>

      <name>echinus</name>
      <bndbox>
         <xmin>1</xmin>
         <ymin>223</ymin>
         <xmax>53</xmax>
         <ymax>281</ymax>
      </bndbox>
   </object>
   
    <object>
		<pose>Unspecified</pose>
		<truncated>0</truncated>
		<difficult>0</difficult>

      <name>echinus</name>
      <bndbox>
         <xmin>113</xmin>
         <ymin>308</ymin>
         <xmax>179</xmax>
         <ymax>365</ymax>
      </bndbox>
   </object>
</annotation>