<?xml version="1.0" encoding="utf-8"?>
    <annotation>
		<size>     
		    <width>1920</width>
		    <height>1080</height>
		    <depth>3</depth>
	    </size>

   <filename>004689.jpg</filename>
   
    <object>
		<pose>Unspecified</pose>
		<truncated>0</truncated>
		<difficult>0</difficult>

      <name>echinus</name>
      <bndbox>
         <xmin>513</xmin>
         <ymin>298</ymin>
         <xmax>592</xmax>
         <ymax>390</ymax>
      </bndbox>
   </object>
   
    <object>
		<pose>Unspecified</pose>
		<truncated>0</truncated>
		<difficult>0</difficult>

      <name>echinus</name>
      <bndbox>
         <xmin>197</xmin>
         <ymin>152</ymin>
         <xmax>247</xmax>
         <ymax>207</ymax>
      </bndbox>
   </object>
   
    <object>
		<pose>Unspecified</pose>
		<truncated>0</truncated>
		<difficult>0</difficult>

      <name>echinus</name>
      <bndbox>
         <xmin>238</xmin>
         <ymin>211</ymin>
         <xmax>298</xmax>
         <ymax>279</ymax>
      </bndbox>
   </object>
</annotation>