<?xml version="1.0" encoding="utf-8"?>
    <annotation>
		<size>     
		    <width>1920</width>
		    <height>1080</height>
		    <depth>3</depth>
	    </size>

   <filename>004822.jpg</filename>
   
    <object>
		<pose>Unspecified</pose>
		<truncated>0</truncated>
		<difficult>0</difficult>

      <name>echinus</name>
      <bndbox>
         <xmin>453</xmin>
         <ymin>224</ymin>
         <xmax>519</xmax>
         <ymax>281</ymax>
      </bndbox>
   </object>
   
    <object>
		<pose>Unspecified</pose>
		<truncated>0</truncated>
		<difficult>0</difficult>

      <name>echinus</name>
      <bndbox>
         <xmin>254</xmin>
         <ymin>217</ymin>
         <xmax>308</xmax>
         <ymax>256</ymax>
      </bndbox>
   </object>
   
    <object>
		<pose>Unspecified</pose>
		<truncated>0</truncated>
		<difficult>0</difficult>

      <name>echinus</name>
      <bndbox>
         <xmin>360</xmin>
         <ymin>49</ymin>
         <xmax>413</xmax>
         <ymax>95</ymax>
      </bndbox>
   </object>
   
    <object>
		<pose>Unspecified</pose>
		<truncated>0</truncated>
		<difficult>0</difficult>

      <name>echinus</name>
      <bndbox>
         <xmin>361</xmin>
         <ymin>15</ymin>
         <xmax>410</xmax>
         <ymax>47</ymax>
      </bndbox>
   </object>
   
    <object>
		<pose>Unspecified</pose>
		<truncated>0</truncated>
		<difficult>0</difficult>

      <name>echinus</name>
      <bndbox>
         <xmin>474</xmin>
         <ymin>4</ymin>
         <xmax>521</xmax>
         <ymax>40</ymax>
      </bndbox>
   </object>
</annotation>