<?xml version="1.0" encoding="utf-8"?>
    <annotation>
		<size>     
		    <width>1920</width>
		    <height>1080</height>
		    <depth>3</depth>
	    </size>

	<filename>v000188.jpg</filename>
	
    <object>
		<pose>Unspecified</pose>
		<truncated>0</truncated>
		<difficult>0</difficult>

		<name>holothurian</name>
		<bndbox>
			<xmin>497</xmin>
			<ymin>639</ymin>
			<xmax>1327</xmax>
			<ymax>1241</ymax>
		</bndbox>
	</object>
	
    <object>
		<pose>Unspecified</pose>
		<truncated>0</truncated>
		<difficult>0</difficult>

		<name>holothurian</name>
		<bndbox>
			<xmin>1792</xmin>
			<ymin>934</ymin>
			<xmax>2441</xmax>
			<ymax>1206</ymax>
		</bndbox>
	</object>
</annotation>