<?xml version="1.0" encoding="utf-8"?>
    <annotation>
		<size>     
		    <width>1920</width>
		    <height>1080</height>
		    <depth>3</depth>
	    </size>

	<filename>v000147.jpg</filename>
	
    <object>
		<pose>Unspecified</pose>
		<truncated>0</truncated>
		<difficult>0</difficult>

		<name>scallop</name>
		<bndbox>
			<xmin>523</xmin>
			<ymin>796</ymin>
			<xmax>901</xmax>
			<ymax>1062</ymax>
		</bndbox>
	</object>
	
    <object>
		<pose>Unspecified</pose>
		<truncated>0</truncated>
		<difficult>0</difficult>

		<name>echinus</name>
		<bndbox>
			<xmin>1283</xmin>
			<ymin>1485</ymin>
			<xmax>2302</xmax>
			<ymax>2161</ymax>
		</bndbox>
	</object>
</annotation>